astra_gui/__about__.py
astra_gui/__init__.py
astra_gui/app.py
astra_gui/cli.py
astra_gui/home_screen.py
astra_gui/close_coupling/__init__.py
astra_gui/close_coupling/basis_dalton.txt
astra_gui/close_coupling/bsplines.py
astra_gui/close_coupling/cc_notebook_page_module.py
astra_gui/close_coupling/clscplng.py
astra_gui/close_coupling/create_cc_notebook.py
astra_gui/close_coupling/dalton.py
astra_gui/close_coupling/lucia.py
astra_gui/close_coupling/molecule.py
astra_gui/help_messages/notification.md
astra_gui/input_file_templates/ASTRA.INP
astra_gui/input_file_templates/CLSCPLNG.INP
astra_gui/input_file_templates/DALTON.INP
astra_gui/input_file_templates/ESSENTIAL_STATES.INP
astra_gui/input_file_templates/EXTERNAL_BASIS_BSPLINES.INP
astra_gui/input_file_templates/LUCIA.INP
astra_gui/input_file_templates/LUCIA_SA.INP
astra_gui/input_file_templates/MOLECULE.INP
astra_gui/input_file_templates/PULSE.INP_Custom
astra_gui/input_file_templates/PULSE.INP_Pump_Probe
astra_gui/input_file_templates/REAL_ESSENTIAL_STATES.INP
astra_gui/input_file_templates/SCATCI.INP
astra_gui/input_file_templates/TDSE.INP
astra_gui/input_file_templates/blank_file
astra_gui/input_file_templates/run_astra_setup.sh
astra_gui/input_file_templates/run_script.sh
astra_gui/input_file_templates/prism_inputs/bspline.inp
astra_gui/input_file_templates/prism_inputs/grids.inp
astra_gui/input_file_templates/prism_inputs/symmetry_config.inp
astra_gui/time_dependent/__init__.py
astra_gui/time_dependent/pulse.py
astra_gui/time_dependent/td_notebook_page_module.py
astra_gui/time_dependent/time_dependent_notebook.py
astra_gui/time_independent/__init__.py
astra_gui/time_independent/pad.py
astra_gui/time_independent/scatt_states.py
astra_gui/time_independent/structural.py
astra_gui/time_independent/ti_notebook_page_module.py
astra_gui/time_independent/time_independent_notebook.py
astra_gui/utils/__init__.py
astra_gui/utils/config_module.py
astra_gui/utils/font_module.py
astra_gui/utils/hover_widget_module.py
astra_gui-1.3.0.dist-info/METADATA
astra_gui-1.3.0.dist-info/WHEEL
astra_gui-1.3.0.dist-info/entry_points.txt
astra_gui-1.3.0.dist-info/licenses/LICENSE.txt
astra_gui-1.3.0.dist-info/RECORD
