Metadata-Version: 2.4
Name: astra_gui
Version: 1.3.0
Summary: A Python Graphical User Interface for the ASTRA program
Project-URL: Documentation, https://github.com/Faria22/astra_gui#readme
Project-URL: Issues, https://github.com/Faria22/astra_gui/issues
Project-URL: Source, https://github.com/Faria22/astra_gui
Author-email: Faria22 <fariafelipe22@hotmail.com>
License-Expression: MIT
License-File: LICENSE.txt
Classifier: Development Status :: 4 - Beta
Classifier: Programming Language :: Python
Classifier: Programming Language :: Python :: 3.11
Classifier: Programming Language :: Python :: 3.12
Classifier: Programming Language :: Python :: 3.13
Classifier: Programming Language :: Python :: Implementation :: CPython
Requires-Python: <3.14,>=3.11
Requires-Dist: moldenviz>=1.8
Requires-Dist: numpy>=2.2
Requires-Dist: paramiko>=4.0
Requires-Dist: psutil>=7.1
Requires-Dist: toml>=0.10
Requires-Dist: ttkwidgets>=0.13
Provides-Extra: dev
Requires-Dist: basedpyright>=1.31.4; extra == 'dev'
Requires-Dist: pytest>=8.4; extra == 'dev'
Requires-Dist: ruff>=0.14; extra == 'dev'
